{
  "type": "minecraft:entity",
  "pools": [
    {
      "rolls": 1,
      "entries": [
        {
          "type": "minecraft:item",
          "name": "legendsawaken:gelatin_crystal_seeds"
        }
      ]
    },
     {
      "rolls": 1,
      "entries": [
        {
          "type": "minecraft:item",
          "name": "legendsawaken:boss_one_music_disc"
        }
      ]
    },
    {
      "rolls": 1,
      "entries": [
        {
          "type": "minecraft:item",
          "name": "legendsawaken:shadow_essence",
          "functions": [
            {
              "function": "minecraft:set_count",
              "count": {
                "type": "minecraft:uniform",
                "min": 4,
                "max": 8
              }
            }
          ]
        }
      ]
    },
     {
      "rolls": 1,
      "entries": [
        {
          "type": "minecraft:item",
          "name": "legendsawaken:vital_crystal_shard",
          "functions": [
            {
              "function": "minecraft:set_count",
              "count": {
                "type": "minecraft:uniform",
                "min": 4,
                "max": 8
              }
            }
          ]
        }
      ]
    },
    {
      "rolls": 1,
      "entries": [
        {
          "type": "minecraft:item",
          "name": "legendsawaken:raw_mythril",
          "functions": [
            {
              "function": "minecraft:set_count",
              "count": {
                "type": "minecraft:uniform",
                "min": 12,
                "max": 24
              }
            }
          ]
        }
      ]
    },
    {
      "rolls": 1,
      "entries": [
        {
          "type": "minecraft:item",
          "name": "legendsawaken:raw_titanite",
          "functions": [
            {
              "function": "minecraft:set_count",
              "count": {
                "type": "minecraft:uniform",
                "min": 12,
                "max": 24
              }
            }
          ]
        }
      ]
    },
    {
      "rolls": 1,
      "entries": [
        {
          "type": "minecraft:item",
          "name": "legendsawaken:crusader_hammer",
         "functions": [
            {
              "function": "minecraft:set_nbt",
              "tag": "{Enchantments:[{id:\"minecraft:sweeping\",lvl:4}]}"
            }
          ]
        },
        {
          "type": "minecraft:item",
          "name": "legendsawaken:barbarian_waraxe"
        }
      ]
    }
  ],
  "random_sequence": "legendsawaken:entities/eye_of_cthulhu"
}
